pylotoncycle/__init__.py
pylotoncycle/parser.py
pylotoncycle/pylotoncycle.py
pylotoncycle-0.9.0.dist-info/licenses/LICENSE
pylotoncycle-0.9.0.dist-info/METADATA
pylotoncycle-0.9.0.dist-info/WHEEL
pylotoncycle-0.9.0.dist-info/top_level.txt
pylotoncycle-0.9.0.dist-info/RECORD
