Metadata-Version: 2.4
Name: pylotoncycle
Version: 0.9.0
Summary: Module to access your Peloton workout data
Home-page: https://github.com/justmedude/pylotoncycle
Author: Vikram Adukia
Author-email: github@fireitup.net
License: BSD
Classifier: Development Status :: 4 - Beta
Classifier: Programming Language :: Python :: 3
License-File: LICENSE
Requires-Dist: requests
Dynamic: author
Dynamic: author-email
Dynamic: classifier
Dynamic: description
Dynamic: description-content-type
Dynamic: home-page
Dynamic: license
Dynamic: license-file
Dynamic: requires-dist
Dynamic: summary
